zensols/dbpg/resources/app.conf
zensols/dbpg/resources/obj.yml
zensols/dbpg/__init__.py
zensols/dbpg/postgres.py
zensols_dbpg-1.5.0.dist-info/METADATA
zensols_dbpg-1.5.0.dist-info/WHEEL
zensols_dbpg-1.5.0.dist-info/licenses/LICENSE.md
zensols_dbpg-1.5.0.dist-info/RECORD
