Metadata-Version: 2.3
Name: zensols_dbpg
Version: 1.5.0
Summary: A PostgreSQL implementation of the dbutil library.
Project-URL: Homepage, https://github.com/plandes/dbpg
Project-URL: Documentation, https://plandes.github.io/dbpg
Project-URL: Repository, https://github.com/plandes/dbpg.git
Project-URL: Issues, https://github.com/plandes/dbpg/issues
Project-URL: Changelog, https://github.com/plandes/dbpg/blob/master/CHANGELOG.md
Author-email: Paul Landes <landes@mailc.net>
License: MIT
Keywords: database,postgres,tooling
Requires-Python: <3.15,>=3.11
Requires-Dist: psycopg2~=2.9.9
Requires-Dist: zensols-db~=1.5.0
